astrospec/__init__.py
astrospec/cli.py
astrospec/light_correction.py
astrospec/postproc.py
astrospec/shape_correction.py
astrospec/spectrum.py
astrospec/utils.py
astrospec/video_reader.py
astrospec-0.2.4.dist-info/LICENSE
astrospec-0.2.4.dist-info/METADATA
astrospec-0.2.4.dist-info/WHEEL
astrospec-0.2.4.dist-info/entry_points.txt
astrospec-0.2.4.dist-info/top_level.txt
astrospec-0.2.4.dist-info/RECORD
